Losses/Mask_bce_loss.py
Losses/Triplet_loss.py
model/CBAM_Face_attention_Resnet_maskV2.py
model/config_mask.py
model/inference.py
model/test.py
Mask_Face_Inference-0.0.1.dist-info/METADATA
Mask_Face_Inference-0.0.1.dist-info/WHEEL
Mask_Face_Inference-0.0.1.dist-info/top_level.txt
Mask_Face_Inference-0.0.1.dist-info/RECORD
